ing/__init__.py
ing/console.py
ing/wikipedia.py
ing-0.1.0.dist-info/entry_points.txt
ing-0.1.0.dist-info/LICENSE
ing-0.1.0.dist-info/WHEEL
ing-0.1.0.dist-info/METADATA
ing-0.1.0.dist-info/RECORD
